dbModel/__init__.py
dbModel/dbModel.py
coursework-0.0.1.dist-info/LICENCE.txt
coursework-0.0.1.dist-info/METADATA
coursework-0.0.1.dist-info/WHEEL
coursework-0.0.1.dist-info/top_level.txt
coursework-0.0.1.dist-info/RECORD
