Metadata-Version: 2.1
Name: coursework
Version: 0.0.1
Summary: Model for CRUD operations with PostgreSQL DB
Home-page: UNKNOWN
Author: Andrii Shevliakov
Author-email: josh@dublocks.org
License: MIT
Platform: UNKNOWN
Classifier: Development Status :: 5 - Production/Stable
Classifier: Intended Audience :: Education
Classifier: Operating System :: Microsoft :: Windows :: Windows 10
Classifier: License :: OSI Approved :: MIT License
Classifier: Programming Language :: Python :: 3.7
